reporters_db/__init__.py
reporters_db/make_csv.py
reporters_db/utils.py
reporters_db/data/case_name_abbreviations.json
reporters_db/data/journals.json
reporters_db/data/laws.json
reporters_db/data/regexes.json
reporters_db/data/reporters.csv
reporters_db/data/reporters.json
reporters_db/data/state_abbreviations.json
reporters_db-3.2.61.dist-info/licenses/LICENSE
reporters_db-3.2.61.dist-info/METADATA
reporters_db-3.2.61.dist-info/WHEEL
reporters_db-3.2.61.dist-info/top_level.txt
reporters_db-3.2.61.dist-info/RECORD
